LICENSE
readme.org
setup.cfg
setup.py
eorg/__init__.py
eorg/cmd.py
eorg/const.py
eorg/generate.py
eorg/helper.py
eorg/parser.py
eorg/test.py
eorg/tokens.py
eorg/version.py
eorg.egg-info/PKG-INFO
eorg.egg-info/SOURCES.txt
eorg.egg-info/dependency_links.txt
eorg.egg-info/requires.txt
eorg.egg-info/top_level.txt