Metadata-Version: 1.1
Name: eorg
Version: 0.82
Summary: Simple org document parser
Home-page: https://gitlab.com/python-open-source-library-collection/eorg
Author: Oliver Marks
Author-email: oly@digitaloctave.com
License:                     GNU GENERAL PUBLIC LICENSE
